guessproj.py
guessproj-0.5.dist-info/DESCRIPTION.rst
guessproj-0.5.dist-info/METADATA
guessproj-0.5.dist-info/RECORD
guessproj-0.5.dist-info/WHEEL
guessproj-0.5.dist-info/entry_points.txt
guessproj-0.5.dist-info/metadata.json
guessproj-0.5.dist-info/top_level.txt
