Metadata-Version: 2.0
Name: guessproj
Version: 0.5
Summary: Script for guessing parameters of cartographic projection
Home-page: https://github.com/Ariki/guessproj
Author: Alexei Ardyakov
Author-email: ardjakov@rambler.ru
License: MIT
Platform: a
Platform: n
Platform: y
Classifier: Development Status :: 4 - Beta
Classifier: Environment :: Console
Classifier: Intended Audience :: Science/Research
Classifier: License :: OSI Approved :: MIT License
Classifier: Natural Language :: English
Classifier: Operating System :: OS Independent
Classifier: Programming Language :: Python
Classifier: Programming Language :: Python :: 2.6
Classifier: Programming Language :: Python :: 2.7
Classifier: Programming Language :: Python :: 3.3
Classifier: Programming Language :: Python :: 3.4
Classifier: Topic :: Scientific/Engineering :: GIS
Classifier: Topic :: Utilities
Requires-Dist: numpy
Requires-Dist: pyproj
Requires-Dist: scipy
Provides-Extra: WKT
Requires-Dist: GDAL; extra == 'WKT'
